adpushup_adstxt/__init__.py
adpushup_adstxt/__init__.pyc
adpushup_adstxt/django_settings.py
adpushup_adstxt/django_views.py
adpushup_adstxt/models.py
adpushup_adstxt/utils.py
adpushup_adstxt-0.1.2.dist-info/METADATA
adpushup_adstxt-0.1.2.dist-info/RECORD
adpushup_adstxt-0.1.2.dist-info/WHEEL
adpushup_adstxt-0.1.2.dist-info/top_level.txt
