Metadata-Version: 2.1
Name: adpushup-adstxt
Version: 0.1.2
Summary: AdPushUp ads.txt management API.
Home-page: https://bitbucket.org/romkenet/adpushup-adstxt/
Author: Roman Barczyński
Author-email: romanb@leanlab.pl
License: UNKNOWN
Platform: UNKNOWN
Classifier: Development Status :: 4 - Beta
Classifier: Environment :: Web Environment
Classifier: Intended Audience :: Developers
Classifier: License :: OSI Approved :: BSD License
Classifier: Operating System :: OS Independent
Classifier: Programming Language :: Python
